<?xml version="1.0" encoding="utf-8"?>
<odoo>
  <data>

    <record id="res_partner_form_view_inherit_l10n_si_tax_registry" model="ir.ui.view">
      <field name="name">res.partner.form.inherit</field>
      <field name="model">res.partner</field>
      <field name="inherit_id" ref="account.view_partner_property_form"/>
      <field name="arch" type="xml">
	  <field name="property_account_payable_id" position="after">
	     <field name="vat" />
	  </field>
	</field>
    </record>

  </data>
</odoo>
